lecture code/05/clkdiv.v
`timescale 1ns/10ps

module clkdiv(
    clk_i,
    rstn_i,
    sel_i,
    dclk_o
);

input   wire            clk_i;
input   wire            rstn_i;
input   wire    [1:0]   sel_i;
output  reg             dclk_o;

reg [7:0]   cnt;



always @(posedge clk_i or negedge rstn_i)
begin
    if( ~rstn_i)
        cnt <= 8'h00;
    else
    begin
        cnt <= cnt + 1;
    end
end


always @(*)
begin
    case(sel_i)
    2'b00:      dclk_o = cnt[7];
    2'b01:      dclk_o = cnt[6];
    2'b10:      dclk_o = cnt[5];
    2'b11:      dclk_o = cnt[4];
    default:    dclk_o = 1'b0;
    endcase
end




endmodule

lecture code/05/top.v
module top(
    clk_i,
    rstn_i,
    sel_i,
    dclk_o,
    en_i,
    unused_o
);

input   wire            clk_i;
input   wire            rstn_i;
input   wire    [1:0]   sel_i;
output  wire            dclk_o;
input   wire            en_i;
output  wire            unused_o;

wire    dclk;

clkdiv clkdiv_inst(
    .clk_i(clk_i), 
    .rstn_i(rstn_i), 
    .sel_i(sel_i),
    .dclk_o(dclk)
);

assign dclk_o = dclk&en_i;

endmodule

lecture code/05/tb.v
`timescale 1ns/10ps

module tb();

reg         clk;
reg         rstn;
reg [1:0]   sel;
reg         en;
wire        dclk;
reg        unused;

top top_inst(
    .clk_i(clk),
    .rstn_i(rstn),
    .sel_i(sel),
    .dclk_o(dclk),
    .en_i(en)
);

realtime period = 10;
reg [2:0] i;

always #(period/2) clk = ~clk;


initial begin
    $dumpvars;
    clk = 1'b0;
    
    for(i = 3'b000; i < 3'b100; i = i + 3'h1)
    begin
        clkcheck(i[1:0], 1'b1, period);
    end
    
    #(100);
    unused = 1'b1;
    $display("SUCCESS");
    $finish;
end



task clkcheck(
    input reg [1:0] sel_t,
    input reg en_t,
    input realtime period_t
);

realtime t;
integer factor;
integer exp;

begin
    sel = sel_t;
    en = en_t;
    
    rstn = 1'b0;
    #(5);
    rstn = 1'b1;
    
    @(posedge dclk);
    t = $realtime;
    @(posedge dclk);
    t = $realtime - t;
    
    factor = 2**(8-sel_t);
    exp = period_t*factor;
    if( t != exp)
    begin
        $display("ERROR!");
        #(100);
        $finish;
    end
    
end
endtask


endmodule

lecture code/05/dump.vcd
$date
	Sat Mar 12 16:12:55 2022
$end
$version
	Icarus Verilog
$end
$timescale
	10ps
$end
$scope module tb $end
$var wire 1 ! dclk $end
$var reg 1 " clk $end
$var reg 1 # en $end
$var reg 3 $ i [2:0] $end
$var reg 1 % rstn $end
$var reg 2 & sel [1:0] $end
$var reg 1 ' unused $end
$var real 1 ( period $end
$scope module top_inst $end
$var wire 1 ) clk_i $end
$var wire 1 * dclk $end
$var wire 1 ! dclk_o $end
$var wire 1 + en_i $end
$var wire 1 , rstn_i $end
$var wire 2 - sel_i [1:0] $end
$var wire 1 . unused_o $end
$scope module clkdiv_inst $end
$var wire 1 ) clk_i $end
$var wire 1 , rstn_i $end
$var wire 2 / sel_i [1:0] $end
$var reg 8 0 cnt [7:0] $end
$var reg 1 1 dclk_o $end
$upscope $end
$upscope $end
$scope task clkcheck $end
$var reg 1 2 en_t $end
$var integer 32 3 exp [31:0] $end
$var integer 32 4 factor [31:0] $end
$var reg 2 5 sel_t [1:0] $end
$var real 1 6 period_t $end
$var real 1 7 t $end
$upscope $end
$upscope $end
$enddefinitions $end
#0
$dumpvars
r0 7
r10 6
b0 5
bx 4
bx 3
12
01
b0 0
b0 /
z.
b0 -
0,
1+
0*
0)
r10 (
x'
b0 &
0%
b0 $
1#
0"
0!
$end
#500
b1 0
1%
1,
1"
1)
#1000
0"
0)
#1500
b10 0
1"
1)
#2000
0"
0)
#2500
b11 0
1"
1)
#3000
0"
0)
#3500
b100 0
1"
1)
#4000
0"
0)
#4500
b101 0
1"
1)
#5000
0"
0)
#5500
b110 0
1"
1)
#6000
0"
0)
#6500
b111 0
1"
1)
#7000
0"
0)
#7500
b1000 0
1"
1)
#8000
0"
0)
#8500
b1001 0
1"
1)
#9000
0"
0)
#9500
b1010 0
1"
1)
#10000
0"
0)
#10500
b1011 0
1"
1)
#11000
0"
0)
#11500
b1100 0
1"
1)
#12000
0"
0)
#12500
b1101 0
1"
1)
#13000
0"
0)
#13500
b1110 0
1"
1)
#14000
0"
0)
#14500
b1111 0
1"
1)
#15000
0"
0)
#15500
b10000 0
1"
1)
#16000
0"
0)
#16500
b10001 0
1"
1)
#17000
0"
0)
#17500
b10010 0
1"
1)
#18000
0"
0)
#18500
b10011 0
1"
1)
#19000
0"
0)
#19500
b10100 0
1"
1)
#20000
0"
0)
#20500
b10101 0
1"
1)
#21000
0"
0)
#21500
b10110 0
1"
1)
#22000
0"
0)
#22500
b10111 0
1"
1)
#23000
0"
0)
#23500
b11000 0
1"
1)
#24000
0"
0)
#24500
b11001 0
1"
1)
#25000
0"
0)
#25500
b11010 0
1"
1)
#26000
0"
0)
#26500
b11011 0
1"
1)
#27000
0"
0)
#27500
b11100 0
1"
1)
#28000
0"
0)
#28500
b11101 0
1"
1)
#29000
0"
0)
#29500
b11110 0
1"
1)
#30000
0"
0)
#30500
b11111 0
1"
1)
#31000
0"
0)
#31500
b100000 0
1"
1)
#32000
0"
0)
#32500
b100001 0
1"
1)
#33000
0"
0)
#33500
b100010 0
1"
1)
#34000
0"
0)
#34500
b100011 0
1"
1)
#35000
0"
0)
#35500
b100100 0
1"
1)
#36000
0"
0)
#36500
b100101 0
1"
1)
#37000
0"
0)
#37500
b100110 0
1"
1)
#38000
0"
0)
#38500
b100111 0
1"
1)
#39000
0"
0)
#39500
b101000 0
1"
1)
#40000
0"
0)
#40500
b101001 0
1"
1)
#41000
0"
0)
#41500
b101010 0
1"
1)
#42000
0"
0)
#42500
b101011 0
1"
1)
#43000
0"
0)
#43500
b101100 0
1"
1)
#44000
0"
0)
#44500
b101101 0
1"
1)
#45000
0"
0)
#45500
b101110 0
1"
1)
#46000
0"
0)
#46500
b101111 0
1"
1)
#47000
0"
0)
#47500
b110000 0
1"
1)
#48000
0"
0)
#48500
b110001 0
1"
1)
#49000
0"
0)
#49500
b110010 0
1"
1)
#50000
0"
0)
#50500
b110011 0
1"
1)
#51000
0"
0)
#51500
b110100 0
1"
1)
#52000
0"
0)
#52500
b110101 0
1"
1)
#53000
0"
0)
#53500
b110110 0
1"
1)
#54000
0"
0)
#54500
b110111 0
1"
1)
#55000
0"
0)
#55500
b111000 0
1"
1)
#56000
0"
0)
#56500
b111001 0
1"
1)
#57000
0"
0)
#57500
b111010 0
1"
1)
#58000
0"
0)
#58500
b111011 0
1"
1)
#59000
0"
0)
#59500
b111100 0
1"
1)
#60000
0"
0)
#60500
b111101 0
1"
1)
#61000
0"
0)
#61500
b111110 0
1"
1)
#62000
0"
0)
#62500
b111111 0
1"
1)
#63000
0"
0)
#63500
b1000000 0
1"
1)
#64000
0"
0)
#64500
b1000001 0
1"
1)
#65000
0"
0)
#65500
b1000010 0
1"
1)
#66000
0"
0)
#66500
b1000011 0
1"
1)
#67000
0"
0)
#67500
b1000100 0
1"
1)
#68000
0"
0)
#68500
b1000101 0
1"
1)
#69000
0"
0)
#69500
b1000110 0
1"
1)
#70000
0"
0)
#70500
b1000111 0
1"
1)
#71000
0"
0)
#71500
b1001000 0
1"
1)
#72000
0"
0)
#72500
b1001001 0
1"
1)
#73000
0"
0)
#73500
b1001010 0
1"
1)
#74000
0"
0)
#74500
b1001011 0
1"
1)
#75000
0"
0)
#75500
b1001100 0
1"
1)
#76000
0"
0)
#76500
b1001101 0
1"
1)
#77000
0"
0)
#77500
b1001110 0
1"
1)
#78000
0"
0)
#78500
b1001111 0
1"
1)
#79000
0"
0)
#79500
b1010000 0
1"
1)
#80000
0"
0)
#80500
b1010001 0
1"
1)
#81000
0"
0)
#81500
b1010010 0
1"
1)
#82000
0"
0)
#82500
b1010011 0
1"
1)
#83000
0"
0)
#83500
b1010100 0
1"
1)
#84000
0"
0)
#84500
b1010101 0
1"
1)
#85000
0"
0)
#85500
b1010110 0
1"
1)
#86000
0"
0)
#86500
b1010111 0
1"
1)
#87000
0"
0)
#87500
b1011000 0
1"
1)
#88000
0"
0)
#88500
b1011001 0
1"
1)
#89000
0"
0)
#89500
b1011010 0
1"
1)
#90000
0"
0)
#90500
b1011011 0
1"
1)
#91000
0"
0)
#91500
b1011100 0
1"
1)
#92000
0"
0)
#92500
b1011101 0
1"
1)
#93000
0"
0)
#93500
b1011110 0
1"
1)
#94000
0"
0)
#94500
b1011111 0
1"
1)
#95000
0"
0)
#95500
b1100000 0
1"
1)
#96000
0"
0)
#96500
b1100001 0
1"
1)
#97000
0"
0)
#97500
b1100010 0
1"
1)
#98000
0"
0)
#98500
b1100011 0
1"
1)
#99000
0"
0)
#99500
b1100100 0
1"
1)
#100000
0"
0)
#100500
b1100101 0
1"
1)
#101000
0"
0)
#101500
b1100110 0
1"
1)
#102000
0"
0)
#102500
b1100111 0
1"
1)
#103000
0"
0)
#103500
b1101000 0
1"
1)
#104000
0"
0)
#104500
b1101001 0
1"
1)
#105000
0"
0)
#105500
b1101010 0
1"
1)
#106000
0"
0)
#106500
b1101011 0
1"
1)
#107000
0"
0)
#107500
b1101100 0
1"
1)
#108000
0"
0)
#108500
b1101101 0
1"
1)
#109000
0"
0)
#109500
b1101110 0
1"
1)
#110000
0"
0)
#110500
b1101111 0
1"
1)
#111000
0"
0)
#111500
b1110000 0
1"
1)
#112000
0"
0)
#112500
b1110001 0
1"
1)
#113000
0"
0)
#113500
b1110010 0
1"
1)
#114000
0"
0)
#114500
b1110011 0
1"
1)
#115000
0"
0)
#115500
b1110100 0
1"
1)
#116000
0"
0)
#116500
b1110101 0
1"
1)
#117000
0"
0)
#117500
b1110110 0
1"
1)
#118000
0"
0)
#118500
b1110111 0
1"
1)
#119000
0"
0)
#119500
b1111000 0
1"
1)
#120000
0"
0)
#120500
b1111001 0
1"
1)
#121000
0"
0)
#121500
b1111010 0
1"
1)
#122000
0"
0)
#122500
b1111011 0
1"
1)
#123000
0"
0)
#123500
b1111100 0
1"
1)
#124000
0"
0)
#124500
b1111101 0
1"
1)
#125000
0"
0)
#125500
b1111110 0
1"
1)
#126000
0"
0)
#126500
b1111111 0
1"
1)
#127000
0"
0)
#127500
r1275 7
1!
11
1*
b10000000 0
1"
1)
#128000
0"
0)
#128500
b10000001 0
1"
1)
#129000
0"
0)
#129500
b10000010 0
1"
1)
#130000
0"
0)
#130500
b10000011 0
1"
1)
#131000
0"
0)
#131500
b10000100 0
1"
1)
#132000
0"
0)
#132500
b10000101 0
1"
1)
#133000
0"
0)
#133500
b10000110 0
1"
1)
#134000
0"
0)
#134500
b10000111 0
1"
1)
#135000
0"
0)
#135500
b10001000 0
1"
1)
#136000
0"
0)
#136500
b10001001 0
1"
1)
#137000
0"
0)
#137500
b10001010 0
1"
1)
#138000
0"
0)
#138500
b10001011 0
1"
1)
#139000
0"
0)
#139500
b10001100 0
1"
1)
#140000
0"
0)
#140500
b10001101 0
1"
1)
#141000
0"
0)
#141500
b10001110 0
1"
1)
#142000
0"
0)
#142500
b10001111 0
1"
1)
#143000
0"
0)
#143500
b10010000 0
1"
1)
#144000
0"
0)
#144500
b10010001 0
1"
1)
#145000
0"
0)
#145500
b10010010 0
1"
1)
#146000
0"
0)
#146500
b10010011 0
1"
1)
#147000
0"
0)
#147500
b10010100 0
1"
1)
#148000
0"
0)
#148500
b10010101 0
1"
1)
#149000
0"
0)
#149500
b10010110 0
1"
1)
#150000
0"
0)
#150500
b10010111 0
1"
1)
#151000
0"
0)
#151500
b10011000 0
1"
1)
#152000
0"
0)
#152500
b10011001 0
1"
1)
#153000
0"
0)
#153500
b10011010 0
1"
1)
#154000
0"
0)
#154500
b10011011 0
1"
1)
#155000
0"
0)
#155500
b10011100 0
1"
1)
#156000
0"
0)
#156500
b10011101 0
1"
1)
#157000
0"
0)
#157500
b10011110 0
1"
1)
#158000
0"
0)
#158500
b10011111 0
1"
1)
#159000
0"
0)
#159500
b10100000 0
1"
1)
#160000
0"
0)
#160500
b10100001 0
1"
1)
#161000
0"
0)
#161500
b10100010 0
1"
1)
#162000
0"
0)
#162500
b10100011 0
1"
1)
#163000
0"
0)
#163500
b10100100 0
1"
1)
#164000
0"
0)
#164500
b10100101 0
1"
1)
#165000
0"
0)
#165500
b10100110 0
1"
1)
#166000
0"
0)
#166500
b10100111 0
1"
1)
#167000
0"
0)
#167500
b10101000 0
1"
1)
#168000
0"
0)
#168500
b10101001 0
1"
1)
#169000
0"
0)
#169500
b10101010 0
1"
1)
#170000
0"
0)
#170500
b10101011 0
1"
1)
#171000
0"
0)
#171500
b10101100 0
1"
1)
#172000
0"
0)
#172500
b10101101 0
1"
1)
#173000
0"
0)
#173500
b10101110 0
1"
1)
#174000
0"
0)
#174500
b10101111 0
1"
1)
#175000
0"
0)
#175500
b10110000 0
1"
1)
#176000
0"
0)
#176500
b10110001 0
1"
1)
#177000
0"
0)
#177500
b10110010 0
1"
1)
#178000
0"
0)
#178500
b10110011 0
1"
1)
#179000
0"
0)
#179500
b10110100 0
1"
1)
#180000
0"
0)
#180500
b10110101 0
1"
1)
#181000
0"
0)
#181500
b10110110 0
1"
1)
#182000
0"
0)
#182500
b10110111 0
1"
1)
#183000
0"
0)
#183500
b10111000 0
1"
1)
#184000
0"
0)
#184500
b10111001 0
1"
1)
#185000
0"
0)
#185500
b10111010 0
1"
1)
#186000
0"
0)
#186500
b10111011 0
1"
1)
#187000
0"
0)
#187500
b10111100 0
1"
1)
#188000
0"
0)
#188500
b10111101 0
1"
1)
#189000
0"
0)
#189500
b10111110 0
1"
1)
#190000
0"
0)
#190500
b10111111 0
1"
1)
#191000
0"
0)
#191500
b11000000 0
1"
1)
#192000
0"
0)
#192500
b11000001 0
1"
1)
#193000
0"
0)
#193500
b11000010 0
1"
1)
#194000
0"
0)
#194500
b11000011 0
1"
1)
#195000
0"
0)
#195500
b11000100 0
1"
1)
#196000
0"
0)
#196500
b11000101 0
1"
1)
#197000
0"
0)
#197500
b11000110 0
1"
1)
#198000
0"
0)
#198500
b11000111 0
1"
1)
#199000
0"
0)
#199500
b11001000 0
1"
1)
#200000
0"
0)
#200500
b11001001 0
1"
1)
#201000
0"
0)
#201500
b11001010 0
1"
1)
#202000
0"
0)
#202500
b11001011 0
1"
1)
#203000
0"
0)
#203500
b11001100 0
1"
1)
#204000
0"
0)
#204500
b11001101 0
1"
1)
#205000
0"
0)
#205500
b11001110 0
1"
1)
#206000
0"
0)
#206500
b11001111 0
1"
1)
#207000
0"
0)
#207500
b11010000 0
1"
1)
#208000
0"
0)
#208500
b11010001 0
1"
1)
#209000
0"
0)
#209500
b11010010 0
1"
1)
#210000
0"
0)
#210500
b11010011 0
1"
1)
#211000
0"
0)
#211500
b11010100 0
1"
1)
#212000
0"
0)
#212500
b11010101 0
1"
1)
#213000
0"
0)
#213500
b11010110 0
1"
1)
#214000
0"
0)
#214500
b11010111 0
1"
1)
#215000
0"
0)
#215500
b11011000 0
1"
1)
#216000
0"
0)
#216500
b11011001 0
1"
1)
#217000
0"
0)
#217500
b11011010 0
1"
1)
#218000
0"
0)
#218500
b11011011 0
1"
1)
#219000
0"
0)
#219500
b11011100 0
1"
1)
#220000
0"
0)
#220500
b11011101 0
1"
1)
#221000
0"
0)
#221500
b11011110 0
1"
1)
#222000
0"
0)
#222500
b11011111 0
1"
1)
#223000
0"
0)
#223500
b11100000 0
1"
1)
#224000
0"
0)
#224500
b11100001 0
1"
1)
#225000
0"
0)
#225500
b11100010 0
1"
1)
#226000
0"
0)
#226500
b11100011 0
1"
1)
#227000
0"
0)
#227500
b11100100 0
1"
1)
#228000
0"
0)
#228500
b11100101 0
1"
1)
#229000
0"
0)
#229500
b11100110 0
1"
1)
#230000
0"
0)
#230500
b11100111 0
1"
1)
#231000
0"
0)
#231500
b11101000 0
1"
1)
#232000
0"
0)
#232500
b11101001 0
1"
1)
#233000
0"
0)
#233500
b11101010 0
1"
1)
#234000
0"
0)
#234500
b11101011 0
1"
1)
#235000
0"
0)
#235500
b11101100 0
1"
1)
#236000
0"
0)
#236500
b11101101 0
1"
1)
#237000
0"
0)
#237500
b11101110 0
1"
1)
#238000
0"
0)
#238500
b11101111 0
1"
1)
#239000
0"
0)
#239500
b11110000 0
1"
1)
#240000
0"
0)
#240500
b11110001 0
1"
1)
#241000
0"
0)
#241500
b11110010 0
1"
1)
#242000
0"
0)
#242500
b11110011 0
1"
1)
#243000
0"
0)
#243500
b11110100 0
1"
1)
#244000
0"
0)
#244500
b11110101 0
1"
1)
#245000
0"
0)
#245500
b11110110 0
1"
1)
#246000
0"
0)
#246500
b11110111 0
1"
1)
#247000
0"
0)
#247500
b11111000 0
1"
1)
#248000
0"
0)
#248500
b11111001 0
1"
1)
#249000
0"
0)
#249500
b11111010 0
1"
1)
#250000
0"
0)
#250500
b11111011 0
1"
1)
#251000
0"
0)
#251500
b11111100 0
1"
1)
#252000
0"
0)
#252500
b11111101 0
1"
1)
#253000
0"
0)
#253500
b11111110 0
1"
1)
#254000
0"
0)
#254500
b11111111 0
1"
1)
#255000
0"
0)
#255500
0!
01
0*
b0 0
1"
1)
#256000
0"
0)
#256500
b1 0
1"
1)
#257000
0"
0)
#257500
b10 0
1"
1)
#258000
0"
0)
#258500
b11 0
1"
1)
#259000
0"
0)
#259500
b100 0
1"
1)
#260000
0"
0)
#260500
b101 0
1"
1)
#261000
0"
0)
#261500
b110 0
1"
1)
#262000
0"
0)
#262500
b111 0
1"
1)
#263000
0"
0)
#263500
b1000 0
1"
1)
#264000
0"
0)
#264500
b1001 0
1"
1)
#265000
0"
0)
#265500
b1010 0
1"
1)
#266000
0"
0)
#266500
b1011 0
1"
1)
#267000
0"
0)
#267500
b1100 0
1"
1)
#268000
0"
0)
#268500
b1101 0
1"
1)
#269000
0"
0)
#269500
b1110 0
1"
1)
#270000
0"
0)
#270500
b1111 0
1"
1)
#271000
0"
0)
#271500
b10000 0
1"
1)
#272000
0"
0)
#272500
b10001 0
1"
1)
#273000
0"
0)
#273500
b10010 0
1"
1)
#274000
0"
0)
#274500
b10011 0
1"
1)
#275000
0"
0)
#275500
b10100 0
1"
1)
#276000
0"
0)
#276500
b10101 0
1"
1)
#277000
0"
0)
#277500
b10110 0
1"
1)
#278000
0"
0)
#278500
b10111 0
1"
1)
#279000
0"
0)
#279500
b11000 0
1"
1)
#280000
0"
0)
#280500
b11001 0
1"
1)
#281000
0"
0)
#281500
b11010 0
1"
1)
#282000
0"
0)
#282500
b11011 0
1"
1)
#283000
0"
0)
#283500
b11100 0
1"
1)
#284000
0"
0)
#284500
b11101 0
1"
1)
#285000
0"
0)
#285500
b11110 0
1"
1)
#286000
0"
0)
#286500
b11111 0
1"
1)
#287000
0"
0)
#287500
b100000 0
1"
1)
#288000
0"
0)
#288500
b100001 0
1"
1)
#289000
0"
0)
#289500
b100010 0
1"
1)
#290000
0"
0)
#290500
b100011 0
1"
1)
#291000
0"
0)
#291500
b100100 0
1"
1)
#292000
0"
0)
#292500
b100101 0
1"
1)
#293000
0"
0)
#293500
b100110 0
1"
1)
#294000
0"
0)
#294500
b100111 0
1"
1)
#295000
0"
0)
#295500
b101000 0
1"
1)
#296000
0"
0)
#296500
b101001 0
1"
1)
#297000
0"
0)
#297500
b101010 0
1"
1)
#298000
0"
0)
#298500
b101011 0
1"
1)
#299000
0"
0)
#299500
b101100 0
1"
1)
#300000
0"
0)
#300500
b101101 0
1"
1)
#301000
0"
0)
#301500
b101110 0
1"
1)
#302000
0"
0)
#302500
b101111 0
1"
1)
#303000
0"
0)
#303500
b110000 0
1"
1)
#304000
0"
0)
#304500
b110001 0
1"
1)
#305000
0"
0)
#305500
b110010 0
1"
1)
#306000
0"
0)
#306500
b110011 0
1"
1)
#307000
0"
0)
#307500
b110100 0
1"
1)
#308000
0"
0)
#308500
b110101 0
1"
1)
#309000
0"
0)
#309500
b110110 0
1"
1)
#310000
0"
0)
#310500
b110111 0
1"
1)
#311000
0"
0)
#311500
b111000 0
1"
1)
#312000
0"
0)
#312500
b111001 0
1"
1)
#313000
0"
0)
#313500
b111010 0
1"
1)
#314000
0"
0)
#314500
b111011 0
1"
1)
#315000
0"
0)
#315500
b111100 0
1"
1)
#316000
0"
0)
#316500
b111101 0
1"
1)
#317000
0"
0)
#317500
b111110 0
1"
1)
#318000
0"
0)
#318500
b111111 0
1"
1)
#319000
0"
0)
#319500
b1000000 0
1"
1)
#320000
0"
0)
#320500
b1000001 0
1"
1)
#321000
0"
0)
#321500
b1000010 0
1"
1)
#322000
0"
0)
#322500
b1000011 0
1"
1)
#323000
0"
0)
#323500
b1000100 0
1"
1)
#324000
0"
0)
#324500
b1000101 0
1"
1)
#325000
0"
0)
#325500
b1000110 0
1"
1)
#326000
0"
0)
#326500
b1000111 0
1"
1)
#327000
0"
0)
#327500
b1001000 0
1"
1)
#328000
0"
0)
#328500
b1001001 0
1"
1)
#329000
0"
0)
#329500
b1001010 0
1"
1)
#330000
0"
0)
#330500
b1001011 0
1"
1)
#331000
0"
0)
#331500
b1001100 0
1"
1)
#332000
0"
0)
#332500
b1001101 0
1"
1)
#333000
0"
0)
#333500
b1001110 0
1"
1)
#334000
0"
0)
#334500
b1001111 0
1"
1)
#335000
0"
0)
#335500
b1010000 0
1"
1)
#336000
0"
0)
#336500
b1010001 0
1"
1)
#337000
0"
0)
#337500
b1010010 0
1"
1)
#338000
0"
0)
#338500
b1010011 0
1"
1)
#339000
0"
0)
#339500
b1010100 0
1"
1)
#340000
0"
0)
#340500
b1010101 0
1"
1)
#341000
0"
0)
#341500
b1010110 0
1"
1)
#342000
0"
0)
#342500
b1010111 0
1"
1)
#343000
0"
0)
#343500
b1011000 0
1"
1)
#344000
0"
0)
#344500
b1011001 0
1"
1)
#345000
0"
0)
#345500
b1011010 0
1"
1)
#346000
0"
0)
#346500
b1011011 0
1"
1)
#347000
0"
0)
#347500
b1011100 0
1"
1)
#348000
0"
0)
#348500
b1011101 0
1"
1)
#349000
0"
0)
#349500
b1011110 0
1"
1)
#350000
0"
0)
#350500
b1011111 0
1"
1)
#351000
0"
0)
#351500
b1100000 0
1"
1)
#352000
0"
0)
#352500
b1100001 0
1"
1)
#353000
0"
0)
#353500
b1100010 0
1"
1)
#354000
0"
0)
#354500
b1100011 0
1"
1)
#355000
0"
0)
#355500
b1100100 0
1"
1)
#356000
0"
0)
#356500
b1100101 0
1"
1)
#357000
0"
0)
#357500
b1100110 0
1"
1)
#358000
0"
0)
#358500
b1100111 0
1"
1)
#359000
0"
0)
#359500
b1101000 0
1"
1)
#360000
0"
0)
#360500
b1101001 0
1"
1)
#361000
0"
0)
#361500
b1101010 0
1"
1)
#362000
0"
0)
#362500
b1101011 0
1"
1)
#363000
0"
0)
#363500
b1101100 0
1"
1)
#364000
0"
0)
#364500
b1101101 0
1"
1)
#365000
0"
0)
#365500
b1101110 0
1"
1)
#366000
0"
0)
#366500
b1101111 0
1"
1)
#367000
0"
0)
#367500
b1110000 0
1"
1)
#368000
0"
0)
#368500
b1110001 0
1"
1)
#369000
0"
0)
#369500
b1110010 0
1"
1)
#370000
0"
0)
#370500
b1110011 0
1"
1)
#371000
0"
0)
#371500
b1110100 0
1"
1)
#372000
0"
0)
#372500
b1110101 0
1"
1)
#373000
0"
0)
#373500
b1110110 0
1"
1)
#374000
0"
0)
#374500
b1110111 0
1"
1)
#375000
0"
0)
#375500
b1111000 0
1"
1)
#376000
0"
0)
#376500
b1111001 0
1"
1)
#377000
0"
0)
#377500
b1111010 0
1"
1)
#378000
0"
0)
#378500
b1111011 0
1"
1)
#379000
0"
0)
#379500
b1111100 0
1"
1)
#380000
0"
0)
#380500
b1111101 0
1"
1)
#381000
0"
0)
#381500
b1111110 0
1"
1)
#382000
0"
0)
#382500
b1111111 0
1"
1)
#383000
0"
0)
#383500
0%
0,
b1 &
b1 -
b1 /
b1 5
b1 $
b101000000000 3
b100000000 4
r2560 7
0!
01
0*
b0 0
1"
1)
#384000
1%
1,
0"
0)
#384500
b1 0
1"
1)
#385000
0"
0)
#385500
b10 0
1"
1)
#386000
0"
0)
#386500
b11 0
1"
1)
#387000
0"
0)
#387500
b100 0
1"
1)
#388000
0"
0)
#388500
b101 0
1"
1)
#389000
0"
0)
#389500
b110 0
1"
1)
#390000
0"
0)
#390500
b111 0
1"
1)
#391000
0"
0)
#391500
b1000 0
1"
1)
#392000
0"
0)
#392500
b1001 0
1"
1)
#393000
0"
0)
#393500
b1010 0
1"
1)
#394000
0"
0)
#394500
b1011 0
1"
1)
#395000
0"
0)
#395500
b1100 0
1"
1)
#396000
0"
0)
#396500
b1101 0
1"
1)
#397000
0"
0)
#397500
b1110 0
1"
1)
#398000
0"
0)
#398500
b1111 0
1"
1)
#399000
0"
0)
#399500
b10000 0
1"
1)
#400000
0"
0)
#400500
b10001 0
1"
1)
#401000
0"
0)
#401500
b10010 0
1"
1)
#402000
0"
0)
#402500
b10011 0
1"
1)
#403000
0"
0)
#403500
b10100 0
1"
1)
#404000
0"
0)
#404500
b10101 0
1"
1)
#405000
0"
0)
#405500
b10110 0
1"
1)
#406000
0"
0)
#406500
b10111 0
1"
1)
#407000
0"
0)
#407500
b11000 0
1"
1)
#408000
0"
0)
#408500
b11001 0
1"
1)
#409000
0"
0)
#409500
b11010 0
1"
1)
#410000
0"
0)
#410500
b11011 0
1"
1)
#411000
0"
0)
#411500
b11100 0
1"
1)
#412000
0"
0)
#412500
b11101 0
1"
1)
#413000
0"
0)
#413500
b11110 0
1"
1)
#414000
0"
0)
#414500
b11111 0
1"
1)
#415000
0"
0)
#415500
b100000 0
1"
1)
#416000
0"
0)
#416500
b100001 0
1"
1)
#417000
0"
0)
#417500
b100010 0
1"
1)
#418000
0"
0)
#418500
b100011 0
1"
1)
#419000
0"
0)
#419500
b100100 0
1"
1)
#420000
0"
0)
#420500
b100101 0
1"
1)
#421000
0"
0)
#421500
b100110 0
1"
1)
#422000
0"
0)
#422500
b100111 0
1"
1)
#423000
0"
0)
#423500
b101000 0
1"
1)
#424000
0"
0)
#424500
b101001 0
1"
1)
#425000
0"
0)
#425500
b101010 0
1"
1)
#426000
0"
0)
#426500
b101011 0
1"
1)
#427000
0"
0)
#427500
b101100 0
1"
1)
#428000
0"
0)
#428500
b101101 0
1"
1)
#429000
0"
0)
#429500
b101110 0
1"
1)
#430000
0"
0)
#430500
b101111 0
1"
1)
#431000
0"
0)
#431500
b110000 0
1"
1)
#432000
0"
0)
#432500
b110001 0
1"
1)
#433000
0"
0)
#433500
b110010 0
1"
1)
#434000
0"
0)
#434500
b110011 0
1"
1)
#435000
0"
0)
#435500
b110100 0
1"
1)
#436000
0"
0)
#436500
b110101 0
1"
1)
#437000
0"
0)
#437500
b110110 0
1"
1)
#438000
0"
0)
#438500
b110111 0
1"
1)
#439000
0"
0)
#439500
b111000 0
1"
1)
#440000
0"
0)
#440500
b111001 0
1"
1)
#441000
0"
0)
#441500
b111010 0
1"
1)
#442000
0"
0)
#442500
b111011 0
1"
1)
#443000
0"
0)
#443500
b111100 0
1"
1)
#444000
0"
0)
#444500
b111101 0
1"
1)
#445000
0"
0)
#445500
b111110 0
1"
1)
#446000
0"
0)
#446500
b111111 0
1"
1)
#447000
0"
0)
#447500
r4475 7
1!
11
1*
b1000000 0
1"
1)
#448000
0"
0)
#448500
b1000001 0
1"
1)
#449000
0"
0)
#449500
b1000010 0
1"
1)
#450000
0"
0)
#450500
b1000011 0
1"
1)
#451000
0"
0)
#451500
b1000100 0
1"
1)
#452000
0"
0)
#452500
b1000101 0
1"
1)
#453000
0"
0)
#453500
b1000110 0
1"
1)
#454000
0"
0)
#454500
b1000111 0
1"
1)
#455000
0"
0)
#455500
b1001000 0
1"
1)
#456000
0"
0)
#456500
b1001001 0
1"
1)
#457000
0"
0)
#457500
b1001010 0
1"
1)
#458000
0"
0)
#458500
b1001011 0
1"
1)
#459000
0"
0)
#459500
b1001100 0
1"
1)
#460000
0"
0)
#460500
b1001101 0
1"
1)
#461000
0"
0)
#461500
b1001110 0
1"
1)
#462000
0"
0)
#462500
b1001111 0
1"
1)
#463000
0"
0)
#463500
b1010000 0
1"
1)
#464000
0"
0)
#464500
b1010001 0
1"
1)
#465000
0"
0)
#465500
b1010010 0
1"
1)
#466000
0"
0)
#466500
b1010011 0
1"
1)
#467000
0"
0)
#467500
b1010100 0
1"
1)
#468000
0"
0)
#468500
b1010101 0
1"
1)
#469000
0"
0)
#469500
b1010110 0
1"
1)
#470000
0"
0)
#470500
b1010111 0
1"
1)
#471000
0"
0)
#471500
b1011000 0
1"
1)
#472000
0"
0)
#472500
b1011001 0
1"
1)
#473000
0"
0)
#473500
b1011010 0
1"
1)
#474000
0"
0)
#474500
b1011011 0
1"
1)
#475000
0"
0)
#475500
b1011100 0
1"
1)
#476000
0"
0)
#476500
b1011101 0
1"
1)
#477000
0"
0)
#477500
b1011110 0
1"
1)
#478000
0"
0)
#478500
b1011111 0
1"
1)
#479000
0"
0)
#479500
b1100000 0
1"
1)
#480000
0"
0)
#480500
b1100001 0
1"
1)
#481000
0"
0)
#481500
b1100010 0
1"
1)
#482000
0"
0)
#482500
b1100011 0
1"
1)
#483000
0"
0)
#483500
b1100100 0
1"
1)
#484000
0"
0)
#484500
b1100101 0
1"
1)
#485000
0"
0)
#485500
b1100110 0
1"
1)
#486000
0"
0)
#486500
b1100111 0
1"
1)
#487000
0"
0)
#487500
b1101000 0
1"
1)
#488000
0"
0)
#488500
b1101001 0
1"
1)
#489000
0"
0)
#489500
b1101010 0
1"
1)
#490000
0"
0)
#490500
b1101011 0
1"
1)
#491000
0"
0)
#491500
b1101100 0
1"
1)
#492000
0"
0)
#492500
b1101101 0
1"
1)
#493000
0"
0)
